async_mqtt_publisher/__init__.py
async_mqtt_publisher/__main__.py
async_mqtt_publisher/choices.py
async_mqtt_publisher/dataclasses.py
async_mqtt_publisher/main.py
async_mqtt_publisher-0.0.8.dist-info/LICENSE
async_mqtt_publisher-0.0.8.dist-info/METADATA
async_mqtt_publisher-0.0.8.dist-info/WHEEL
async_mqtt_publisher-0.0.8.dist-info/top_level.txt
async_mqtt_publisher-0.0.8.dist-info/RECORD
